nltools/__init__.py
nltools/analysis.py
nltools/cross_validation.py
nltools/datasets.py
nltools/file_reader.py
nltools/mask.py
nltools/plotting.py
nltools/prefs.py
nltools/simulator.py
nltools/stats.py
nltools/utils.py
nltools/version.py
nltools/data/__init__.py
nltools/data/adjacency.py
nltools/data/brain_data.py
nltools/data/design_matrix.py
nltools/external/__init__.py
nltools/external/hrf.py
nltools/external/srm.py
nltools/resources/MNI152_T1_2mm.nii.gz
nltools/resources/MNI152_T1_2mm_brain.nii.gz
nltools/resources/MNI152_T1_2mm_brain_mask.nii.gz
nltools/resources/MNI152_T1_2mm_brain_mask_no_ventricles.nii.gz
nltools/resources/MNI152_T1_3mm.nii.gz
nltools/resources/MNI152_T1_3mm_brain.nii.gz
nltools/resources/MNI152_T1_3mm_brain_mask.nii.gz
nltools/resources/MNI152_T1_3mm_brain_mask_no_ventricles.nii.gz
nltools/resources/covariates_example.csv
nltools/resources/gm_mask_2mm.nii.gz
nltools/resources/gm_mask_3mm.nii.gz
nltools/resources/onsets_example.txt
nltools/resources/onsets_example_with_dur.txt
nltools-0.5.1.dist-info/LICENSE
nltools-0.5.1.dist-info/METADATA
nltools-0.5.1.dist-info/WHEEL
nltools-0.5.1.dist-info/top_level.txt
nltools-0.5.1.dist-info/RECORD
